wiki_440_version_helper/__init__.py
wiki_440_version_helper/wiki_440_version_helper.py
wiki_440_version_helper-0.3.dist-info/METADATA
wiki_440_version_helper-0.3.dist-info/RECORD
wiki_440_version_helper-0.3.dist-info/WHEEL
wiki_440_version_helper-0.3.dist-info/top_level.txt
