Metadata-Version: 2.1
Name: wiki-440-version-helper
Version: 0.3
Summary: A small package for a class project
Home-page: UNKNOWN
Author: dlgulley411
Author-email: UNKNOWN
License: UNKNOWN
Platform: UNKNOWN
